{
  "name": "osgl-new",
  "tree": {
    "$className": "DataModel",
    "ReplicatedStorage": {
      "OSGL": {
        "$path": "src"
      }
    },
    "ServerScriptService": {
      "Tests": {
        "$path": "tests/server"
      }
    },
    "StarterPlayer": {
      "StarterPlayerScripts": {
        "Tests": {
          "$path": "tests/client"
        }
      }
    },

    "ServerStorage": {
      "osgl-image-uploader": {
        "OSGL": {
          "$path": "src"
        },
        
        "$path": "plugins/image"
      }
    }
  }
}